{
 "actions": [],
 "allow_rename": 1,
 "creation": "2022-08-11 09:39:31.744820",
 "doctype": "DocType",
 "editable_grid": 1,
 "engine": "InnoDB",
 "field_order": [
  "name_of_beneficiary",
  "sex",
  "age",
  "contact_number",
  "training_institution",
  "amount"
 ],
 "fields": [
  {
   "allow_in_quick_entry": 1,
   "fieldname": "name_of_beneficiary",
   "fieldtype": "Data",
   "in_list_view": 1,
   "in_preview": 1,
   "label": "Name of Beneficiary"
  },
  {
   "allow_in_quick_entry": 1,
   "fieldname": "sex",
   "fieldtype": "Link",
   "in_list_view": 1,
   "in_preview": 1,
   "label": "Sex",
   "options": "Gender"
  },
  {
   "allow_in_quick_entry": 1,
   "fieldname": "age",
   "fieldtype": "Int",
   "in_list_view": 1,
   "in_preview": 1,
   "label": "Age"
  },
  {
   "allow_in_quick_entry": 1,
   "fieldname": "training_institution",
   "fieldtype": "Data",
   "in_list_view": 1,
   "in_preview": 1,
   "label": "Training Institution"
  },
  {
   "allow_in_quick_entry": 1,
   "fieldname": "amount",
   "fieldtype": "Currency",
   "in_list_view": 1,
   "in_preview": 1,
   "label": "Amount"
  },
  {
   "fieldname": "contact_number",
   "fieldtype": "Data",
   "label": "Contact number"
  }
 ],
 "index_web_pages_for_search": 1,
 "istable": 1,
 "links": [],
 "modified": "2022-10-28 23:42:01.971983",
 "modified_by": "Administrator",
 "module": "Cdf Management",
 "name": "Skills DevelopmentTB",
 "owner": "Administrator",
 "permissions": [],
 "sort_field": "modified",
 "sort_order": "DESC",
 "states": []
}